flyingrat/__init__.py
flyingrat/cli.py
flyingrat/pop3.py
flyingrat/store.py
flyingrat-0.1.0.dist-info/DESCRIPTION.rst
flyingrat-0.1.0.dist-info/entry_points.txt
flyingrat-0.1.0.dist-info/LICENSE.txt
flyingrat-0.1.0.dist-info/METADATA
flyingrat-0.1.0.dist-info/metadata.json
flyingrat-0.1.0.dist-info/RECORD
flyingrat-0.1.0.dist-info/top_level.txt
flyingrat-0.1.0.dist-info/WHEEL
