Metadata-Version: 2.0
Name: flyingrat
Version: 0.1.0
Summary: Simple mail server for local development
Home-page: https://github.com/roam/flyingrat/
Author: Kevin Wetzels
Author-email: kevin@roam.be
License: BSD
Platform: UNKNOWN
Classifier: Development Status :: 5 - Production/Stable
Classifier: Environment :: Web Environment
Classifier: Intended Audience :: Developers
Classifier: License :: OSI Approved :: BSD License
Classifier: Operating System :: OS Independent
Classifier: Programming Language :: Python
Classifier: Programming Language :: Python :: 2.7
Requires-Dist: Click
